azure/mgmt/marketplaceordering/__init__.py
azure/mgmt/marketplaceordering/marketplace_ordering_agreements.py
azure/mgmt/marketplaceordering/version.py
azure/mgmt/marketplaceordering/models/__init__.py
azure/mgmt/marketplaceordering/models/agreement_terms.py
azure/mgmt/marketplaceordering/models/agreement_terms_py3.py
azure/mgmt/marketplaceordering/models/error_response.py
azure/mgmt/marketplaceordering/models/error_response_error.py
azure/mgmt/marketplaceordering/models/error_response_error_py3.py
azure/mgmt/marketplaceordering/models/error_response_py3.py
azure/mgmt/marketplaceordering/models/operation.py
azure/mgmt/marketplaceordering/models/operation_display.py
azure/mgmt/marketplaceordering/models/operation_display_py3.py
azure/mgmt/marketplaceordering/models/operation_paged.py
azure/mgmt/marketplaceordering/models/operation_py3.py
azure/mgmt/marketplaceordering/models/resource.py
azure/mgmt/marketplaceordering/models/resource_py3.py
azure/mgmt/marketplaceordering/operations/__init__.py
azure/mgmt/marketplaceordering/operations/marketplace_agreements_operations.py
azure/mgmt/marketplaceordering/operations/operations.py
azure_mgmt_marketplaceordering-0.2.1.dist-info/METADATA
azure_mgmt_marketplaceordering-0.2.1.dist-info/WHEEL
azure_mgmt_marketplaceordering-0.2.1.dist-info/top_level.txt
azure_mgmt_marketplaceordering-0.2.1.dist-info/RECORD
